{
  "fingerprint": "7531dc3cabd97061",
  "companies": {
    "ATCO-B.ST": {
      "pct": 93.75,
      "trusted": 48,
      "matched": 45,
      "years": [
        2022,
        2023
      ],
      "per_statement": {
        "income_statement": {
          "trusted": 16,
          "matched": 16,
          "pct": 100.0
        },
        "balance_sheet": {
          "trusted": 20,
          "matched": 18,
          "pct": 90.0
        },
        "cash_flow_statement": {
          "trusted": 12,
          "matched": 11,
          "pct": 91.67
        }
      }
    },
    "SAND.ST": {
      "pct": 100.0,
      "trusted": 50,
      "matched": 50,
      "years": [
        2023,
        2024
      ],
      "per_statement": {
        "income_statement": {
          "trusted": 16,
          "matched": 16,
          "pct": 100.0
        },
        "balance_sheet": {
          "trusted": 22,
          "matched": 22,
          "pct": 100.0
        },
        "cash_flow_statement": {
          "trusted": 12,
          "matched": 12,
          "pct": 100.0
        }
      }
    },
    "ASML.AS": {
      "pct": 100.0,
      "trusted": 52,
      "matched": 52,
      "years": [
        2024,
        2025
      ],
      "per_statement": {
        "income_statement": {
          "trusted": 18,
          "matched": 18,
          "pct": 100.0
        },
        "balance_sheet": {
          "trusted": 22,
          "matched": 22,
          "pct": 100.0
        },
        "cash_flow_statement": {
          "trusted": 12,
          "matched": 12,
          "pct": 100.0
        }
      }
    },
    "NESN.SW": {
      "pct": 96.0,
      "trusted": 50,
      "matched": 48,
      "years": [
        2023,
        2024
      ],
      "per_statement": {
        "income_statement": {
          "trusted": 14,
          "matched": 14,
          "pct": 100.0
        },
        "balance_sheet": {
          "trusted": 24,
          "matched": 24,
          "pct": 100.0
        },
        "cash_flow_statement": {
          "trusted": 12,
          "matched": 10,
          "pct": 83.33
        }
      }
    },
    "BAS.DE": {
      "pct": 65.38,
      "trusted": 52,
      "matched": 34,
      "years": [
        2023,
        2024
      ],
      "per_statement": {
        "income_statement": {
          "trusted": 20,
          "matched": 2,
          "pct": 10.0
        },
        "balance_sheet": {
          "trusted": 20,
          "matched": 20,
          "pct": 100.0
        },
        "cash_flow_statement": {
          "trusted": 12,
          "matched": 12,
          "pct": 100.0
        }
      }
    },
    "NOVO-B.CO": {
      "pct": 100.0,
      "trusted": 50,
      "matched": 50,
      "years": [
        2023,
        2024
      ],
      "per_statement": {
        "income_statement": {
          "trusted": 16,
          "matched": 16,
          "pct": 100.0
        },
        "balance_sheet": {
          "trusted": 22,
          "matched": 22,
          "pct": 100.0
        },
        "cash_flow_statement": {
          "trusted": 12,
          "matched": 12,
          "pct": 100.0
        }
      }
    },
    "MC.PA": {
      "pct": 87.5,
      "trusted": 32,
      "matched": 28,
      "years": [
        2023,
        2024
      ],
      "per_statement": {
        "income_statement": {
          "trusted": 12,
          "matched": 10,
          "pct": 83.33
        },
        "balance_sheet": {
          "trusted": 16,
          "matched": 14,
          "pct": 87.5
        },
        "cash_flow_statement": {
          "trusted": 4,
          "matched": 4,
          "pct": 100.0
        }
      }
    }
  },
  "skipped": {},
  "total_trusted": 334,
  "total_matched": 307,
  "aggregate_pct": 91.92,
  "measured_companies": 7
}